{"stat.useItem.22":880,"stat.walkOneCm":361983,"stat.useItem.113":261,"stat.useItem.69":5,"stat.useItem.77":5,"stat.jump":673,"stat.useItem.126":33,"stat.useItem.323":15,"stat.fallOneCm":569,"stat.useItem.70":2,"achievement.exploreAllBiomes":{"value":0,"progress":["Plains","Hell"]},"stat.useItem.42":280,"stat.useItem.87":33,"stat.useItem.133":1329,"stat.useItem.137":14,"stat.useItem.41":1155,"achievement.openInventory":82,"stat.useItem.259":3,"stat.damageTaken":22,"stat.useItem.49":84,"stat.flyOneCm":499377,"stat.deaths":8,"stat.useItem.12":11,"stat.drop":15,"stat.playOneMinute":128834,"stat.useItem.3":19,"stat.damageDealt":150}